ai_monitoring/__init__.py
ai_monitoring-0.0.1.dist-info/METADATA
ai_monitoring-0.0.1.dist-info/WHEEL
ai_monitoring-0.0.1.dist-info/RECORD
